timetrans.py
timetrans-2.0.2.dist-info/WHEEL
timetrans-2.0.2.dist-info/METADATA
timetrans-2.0.2.dist-info/RECORD
