Metadata-Version: 2.1
Name: timetrans
Version: 2.0.2
Summary: Time trans to transfer to a normal date and clearance 
Author: Sad_Cat0326
Requires-Python: >=3.7,<4.0
Classifier: Programming Language :: Python :: 3
Classifier: Programming Language :: Python :: 3.7
Classifier: Programming Language :: Python :: 3.8
Classifier: Programming Language :: Python :: 3.9
Classifier: Programming Language :: Python :: 3.10
Classifier: Programming Language :: Python :: 3.11
Requires-Dist: googletrans (==3.1.0a0)
